transformers_rlfh/__init__.py
transformers_rlfh/generate.py
transformers_rlfh/pad.py
transformers_rlfh/store.py
transformers_rlfh/types.py
transformers_rlfh/datasets/__init__.py
transformers_rlfh/datasets/best_of_n_collator.py
transformers_rlfh/datasets/rank_to_pairwise.py
transformers_rlfh/loss/__init__.py
transformers_rlfh/loss/gae.py
transformers_rlfh/models/__init__.py
transformers_rlfh/models/actor_critic.py
transformers_rlfh/models/gpt_best_of_n.py
transformers_rlfh-0.0.1.dev4.dist-info/METADATA
transformers_rlfh-0.0.1.dev4.dist-info/WHEEL
transformers_rlfh-0.0.1.dev4.dist-info/top_level.txt
transformers_rlfh-0.0.1.dev4.dist-info/RECORD
